{
  "properties": [
    {
      "name": "vip.api.clientId",
      "type": "java.lang.String",
      "description": "唯享客clientId",
      "defaultValue": "1"
    },
    {
      "name": "vip.api.clientSecret",
      "type": "java.lang.String",
      "description": "唯享客clientSecret",
      "defaultValue": "1"
    },
    {
      "name": "vip.api.client.connectionTimeoutMillis",
      "type": "java.lang.Integer",
      "description": "唯享客client超时时间",
      "defaultValue": "300"
    },
    {
      "name": "vip.api.client.connectionRequestTimeout",
      "type": "java.lang.Integer",
      "description": "唯享客client请求超时时间",
      "defaultValue": "300"
    },
    {
      "name": "vip.api.clientClassName",
      "type": "java.lang.String",
      "description": "唯享客client请求超时时间",
      "defaultValue": "300"
    }
  ]
}